echofish_aws_resample_and_write_to_zarr_store_lambda/__init__.py
echofish_aws_resample_and_write_to_zarr_store_lambda/dynamo_operations.py
echofish_aws_resample_and_write_to_zarr_store_lambda/lambda_executor.py
echofish_aws_resample_and_write_to_zarr_store_lambda/lambda_handler.py
echofish_aws_resample_and_write_to_zarr_store_lambda/s3_operations.py
echofish_aws_resample_and_write_to_zarr_store_lambda/s3fs_operations.py
echofish_aws_resample_and_write_to_zarr_store_lambda/sns_operations.py
echofish_aws_resample_and_write_to_zarr_store_lambda-1.0.0.dist-info/LICENSE
echofish_aws_resample_and_write_to_zarr_store_lambda-1.0.0.dist-info/METADATA
echofish_aws_resample_and_write_to_zarr_store_lambda-1.0.0.dist-info/WHEEL
echofish_aws_resample_and_write_to_zarr_store_lambda-1.0.0.dist-info/top_level.txt
echofish_aws_resample_and_write_to_zarr_store_lambda-1.0.0.dist-info/RECORD
